{
  "pairs": {
    "polygon:LINK/USDC:UNI->ODOS": {},
    "polygon:WMATIC/USDC:UNI->ODOS": {
      "lastSentAt": 1767078041,
      "lastSentProfit": 10.687015503875966,
      "lastUniswap": 0.1032,
      "lastOdos": 0.114229
    },
    "polygon:LINK:USDC:1000": {
      "samples": [
        {
          "t": 1767181593,
          "p": -2.6639497000000003
        },
        {
          "t": 1767182099,
          "p": -2.6987490999999997
        },
        {
          "t": 1767188745,
          "p": -2.7650093
        },
        {
          "t": 1767189470,
          "p": -2.6021935
        },
        {
          "t": 1767192236,
          "p": -2.8716953
        },
        {
          "t": 1767192937,
          "p": -2.4381544
        },
        {
          "t": 1767195644,
          "p": -2.6168812
        },
        {
          "t": 1767196303,
          "p": -2.3574786
        },
        {
          "t": 1767199904,
          "p": -2.6877827
        },
        {
          "t": 1767202755,
          "p": -2.8223359
        },
        {
          "t": 1767203337,
          "p": -2.8045932
        },
        {
          "t": 1767203868,
          "p": -2.7802798
        },
        {
          "t": 1767207316,
          "p": -2.7372134
        },
        {
          "t": 1767209309,
          "p": -2.8101098
        },
        {
          "t": 1767210156,
          "p": -2.7665324
        },
        {
          "t": 1767210821,
          "p": -2.8475878999999997
        },
        {
          "t": 1767213679,
          "p": -3.0671491
        },
        {
          "t": 1767214526,
          "p": -2.7958797
        },
        {
          "t": 1767216857,
          "p": -2.5638011
        },
        {
          "t": 1767217596,
          "p": -2.4795016999999997
        },
        {
          "t": 1767218124,
          "p": -2.4723143
        },
        {
          "t": 1767220971,
          "p": -2.7988226000000003
        },
        {
          "t": 1767221708,
          "p": -2.7292151000000002
        },
        {
          "t": 1767224054,
          "p": -2.7383481
        },
        {
          "t": 1767224956,
          "p": -2.8016901
        },
        {
          "t": 1767225477,
          "p": -2.9360449
        },
        {
          "t": 1767241135,
          "p": -3.081874
        },
        {
          "t": 1767246319,
          "p": -2.4614454
        },
        {
          "t": 1767247142,
          "p": -2.4855092
        },
        {
          "t": 1767250909,
          "p": -2.7758944
        }
      ],
      "lastAnyAt": 1767250909
    },
    "polygon:MATIC:USDC:1000": {
      "samples": [
        {
          "t": 1767085351,
          "p": -2.8812634999999998
        },
        {
          "t": 1767088406,
          "p": -2.5753728
        }
      ],
      "lastAnyAt": 1767088406
    },
    "polygon:AAVE:USDC:1000": {
      "samples": [
        {
          "t": 1767181598,
          "p": -2.3890293
        },
        {
          "t": 1767182105,
          "p": -2.4537411
        },
        {
          "t": 1767188756,
          "p": -2.4445446
        },
        {
          "t": 1767189477,
          "p": -2.2344865
        },
        {
          "t": 1767192246,
          "p": -2.7493593
        },
        {
          "t": 1767192945,
          "p": -2.2986766
        },
        {
          "t": 1767195648,
          "p": -2.4935248
        },
        {
          "t": 1767196309,
          "p": -2.2539673
        },
        {
          "t": 1767199915,
          "p": -2.5441243
        },
        {
          "t": 1767202764,
          "p": -2.5281996
        },
        {
          "t": 1767203345,
          "p": -2.477748
        },
        {
          "t": 1767203875,
          "p": -2.3493727
        },
        {
          "t": 1767207323,
          "p": -2.4167477
        },
        {
          "t": 1767209315,
          "p": -2.4538941000000003
        },
        {
          "t": 1767210163,
          "p": -2.5622475
        },
        {
          "t": 1767210829,
          "p": -2.5804821
        },
        {
          "t": 1767213687,
          "p": -2.5092052
        },
        {
          "t": 1767214532,
          "p": -2.544606
        },
        {
          "t": 1767216861,
          "p": -2.2459177
        },
        {
          "t": 1767217601,
          "p": -2.2395998
        },
        {
          "t": 1767218130,
          "p": -2.2674768000000003
        },
        {
          "t": 1767220977,
          "p": -2.3468541999999997
        },
        {
          "t": 1767221712,
          "p": -2.3788226999999997
        },
        {
          "t": 1767224063,
          "p": -2.4607386
        },
        {
          "t": 1767224962,
          "p": -2.4830293
        },
        {
          "t": 1767225482,
          "p": -2.543431
        },
        {
          "t": 1767241141,
          "p": -2.4632585
        },
        {
          "t": 1767246324,
          "p": -2.4228184
        },
        {
          "t": 1767247148,
          "p": -2.4383153
        },
        {
          "t": 1767250915,
          "p": -2.5315426
        }
      ],
      "lastAnyAt": 1767250915
    },
    "polygon:LINK:USDC:100": {
      "samples": [
        {
          "t": 1767181593,
          "p": -1.128312
        },
        {
          "t": 1767182098,
          "p": -1.164998
        },
        {
          "t": 1767188744,
          "p": -1.246709
        },
        {
          "t": 1767189469,
          "p": -1.087288
        },
        {
          "t": 1767192233,
          "p": -1.3190199999999999
        },
        {
          "t": 1767192934,
          "p": -0.889819
        },
        {
          "t": 1767195643,
          "p": -1.0477770000000002
        },
        {
          "t": 1767196303,
          "p": -0.7885599999999999
        },
        {
          "t": 1767199903,
          "p": -1.159088
        },
        {
          "t": 1767202753,
          "p": -1.293561
        },
        {
          "t": 1767203336,
          "p": -1.274945
        },
        {
          "t": 1767203867,
          "p": -1.195754
        },
        {
          "t": 1767207315,
          "p": -1.207443
        },
        {
          "t": 1767209308,
          "p": -1.271304
        },
        {
          "t": 1767210156,
          "p": -1.225565
        },
        {
          "t": 1767210819,
          "p": -1.334112
        },
        {
          "t": 1767213679,
          "p": -1.531307
        },
        {
          "t": 1767214525,
          "p": -1.255704
        },
        {
          "t": 1767216857,
          "p": -0.984914
        },
        {
          "t": 1767217595,
          "p": -0.878558
        },
        {
          "t": 1767218124,
          "p": -0.9036829999999999
        },
        {
          "t": 1767220967,
          "p": -1.2385059999999999
        },
        {
          "t": 1767221707,
          "p": -1.169832
        },
        {
          "t": 1767224053,
          "p": -1.220966
        },
        {
          "t": 1767224955,
          "p": -1.259071
        },
        {
          "t": 1767225475,
          "p": -1.396734
        },
        {
          "t": 1767241133,
          "p": -1.516343
        },
        {
          "t": 1767246318,
          "p": -0.912601
        },
        {
          "t": 1767247141,
          "p": -0.9369000000000001
        },
        {
          "t": 1767250908,
          "p": -1.2380769999999999
        }
      ],
      "lastAnyAt": 1767250908
    },
    "polygon:LINK:USDC:3000": {
      "samples": [
        {
          "t": 1767181594,
          "p": -6.2674395999999994
        },
        {
          "t": 1767182100,
          "p": -6.292742033333333
        },
        {
          "t": 1767188747,
          "p": -6.362704933333334
        },
        {
          "t": 1767189471,
          "p": -6.215023633333333
        },
        {
          "t": 1767192239,
          "p": -6.454525299999999
        },
        {
          "t": 1767192938,
          "p": -6.0537809
        },
        {
          "t": 1767195645,
          "p": -6.249765
        },
        {
          "t": 1767196304,
          "p": -5.995686433333333
        },
        {
          "t": 1767199908,
          "p": -6.331902400000001
        },
        {
          "t": 1767202756,
          "p": -6.466888866666666
        },
        {
          "t": 1767203339,
          "p": -6.4272766
        },
        {
          "t": 1767203869,
          "p": -6.431739
        },
        {
          "t": 1767207317,
          "p": -6.356293333333333
        },
        {
          "t": 1767209309,
          "p": -6.426353233333333
        },
        {
          "t": 1767210158,
          "p": -6.3943872
        },
        {
          "t": 1767210823,
          "p": -6.439789433333333
        },
        {
          "t": 1767213682,
          "p": -6.691502666666667
        },
        {
          "t": 1767214527,
          "p": -6.447234033333333
        },
        {
          "t": 1767216858,
          "p": -6.213889766666666
        },
        {
          "t": 1767217597,
          "p": -6.1397978
        },
        {
          "t": 1767218125,
          "p": -6.136782166666667
        },
        {
          "t": 1767220972,
          "p": -6.434558133333333
        },
        {
          "t": 1767221709,
          "p": -6.351405333333333
        },
        {
          "t": 1767224055,
          "p": -6.365276733333333
        },
        {
          "t": 1767224959,
          "p": -6.418156199999999
        },
        {
          "t": 1767225478,
          "p": -6.5436255999999995
        },
        {
          "t": 1767241136,
          "p": -6.712817066666667
        },
        {
          "t": 1767246320,
          "p": -6.1431919
        },
        {
          "t": 1767247143,
          "p": -6.1596484333333335
        },
        {
          "t": 1767250910,
          "p": -6.3875522
        }
      ],
      "lastAnyAt": 1767250910
    },
    "polygon:WMATIC:USDC:1000": {
      "samples": [
        {
          "t": 1767181595,
          "p": -1.5482946
        },
        {
          "t": 1767182102,
          "p": -1.5955457
        },
        {
          "t": 1767188752,
          "p": -2.0519993
        },
        {
          "t": 1767189472,
          "p": -1.7758756
        },
        {
          "t": 1767192243,
          "p": -2.0122086
        },
        {
          "t": 1767192940,
          "p": -1.5378098999999998
        },
        {
          "t": 1767195646,
          "p": -1.7761477
        },
        {
          "t": 1767196306,
          "p": -1.7097279
        },
        {
          "t": 1767199910,
          "p": -1.7473569000000002
        },
        {
          "t": 1767202759,
          "p": -1.9331391
        },
        {
          "t": 1767203342,
          "p": -1.9766301
        },
        {
          "t": 1767203871,
          "p": -1.9681059
        },
        {
          "t": 1767207318,
          "p": -1.8015717
        },
        {
          "t": 1767209312,
          "p": -1.6778738000000002
        },
        {
          "t": 1767210161,
          "p": -1.7589725
        },
        {
          "t": 1767210825,
          "p": -1.7330758000000002
        },
        {
          "t": 1767213684,
          "p": -2.0095153
        },
        {
          "t": 1767214529,
          "p": -1.791287
        },
        {
          "t": 1767216859,
          "p": -1.4355736
        },
        {
          "t": 1767217599,
          "p": -1.2224759
        },
        {
          "t": 1767218126,
          "p": -1.3984333999999998
        },
        {
          "t": 1767220973,
          "p": -1.8766595000000001
        },
        {
          "t": 1767221710,
          "p": -1.9372239999999998
        },
        {
          "t": 1767224057,
          "p": -1.8670935
        },
        {
          "t": 1767224961,
          "p": -1.9511524999999998
        },
        {
          "t": 1767225480,
          "p": -2.0620539
        },
        {
          "t": 1767241138,
          "p": -2.1893072
        },
        {
          "t": 1767246321,
          "p": -1.6177027
        },
        {
          "t": 1767247145,
          "p": -1.4209857
        },
        {
          "t": 1767250912,
          "p": -1.8221054
        }
      ],
      "lastAnyAt": 1767250912
    },
    "polygon:WMATIC:USDC:100": {
      "samples": [
        {
          "t": 1767181595,
          "p": -0.731329
        },
        {
          "t": 1767182102,
          "p": -0.802685
        },
        {
          "t": 1767188750,
          "p": -1.079166
        },
        {
          "t": 1767189472,
          "p": -0.816879
        },
        {
          "t": 1767192242,
          "p": -0.973677
        },
        {
          "t": 1767192939,
          "p": -0.7838609999999999
        },
        {
          "t": 1767195646,
          "p": -0.972079
        },
        {
          "t": 1767196304,
          "p": -0.906451
        },
        {
          "t": 1767199910,
          "p": -0.803706
        },
        {
          "t": 1767202758,
          "p": -1.022581
        },
        {
          "t": 1767203341,
          "p": -1.075465
        },
        {
          "t": 1767203869,
          "p": -1.090625
        },
        {
          "t": 1767207317,
          "p": -0.825114
        },
        {
          "t": 1767209311,
          "p": -0.6921390000000001
        },
        {
          "t": 1767210159,
          "p": -0.801836
        },
        {
          "t": 1767210825,
          "p": -0.753627
        },
        {
          "t": 1767213683,
          "p": -0.93532
        },
        {
          "t": 1767214528,
          "p": -0.672382
        },
        {
          "t": 1767216858,
          "p": -0.5803649999999999
        },
        {
          "t": 1767217598,
          "p": -0.46964900000000004
        },
        {
          "t": 1767218125,
          "p": -0.670126
        },
        {
          "t": 1767220973,
          "p": -1.0990689999999999
        },
        {
          "t": 1767221710,
          "p": -1.013218
        },
        {
          "t": 1767224056,
          "p": -0.96118
        },
        {
          "t": 1767224960,
          "p": -1.049105
        },
        {
          "t": 1767225479,
          "p": -1.081151
        },
        {
          "t": 1767241137,
          "p": -1.092235
        },
        {
          "t": 1767246320,
          "p": -0.641289
        },
        {
          "t": 1767247143,
          "p": -0.497579
        },
        {
          "t": 1767250911,
          "p": -0.978312
        }
      ],
      "lastAnyAt": 1767250911
    },
    "polygon:WMATIC:USDC:3000": {
      "samples": [
        {
          "t": 1767181596,
          "p": -3.565637866666667
        },
        {
          "t": 1767182103,
          "p": -3.5907031666666667
        },
        {
          "t": 1767188754,
          "p": -4.043040433333333
        },
        {
          "t": 1767189473,
          "p": -3.7972145
        },
        {
          "t": 1767192244,
          "p": -4.034946633333333
        },
        {
          "t": 1767192942,
          "p": -3.5585033000000004
        },
        {
          "t": 1767195647,
          "p": -3.7972395
        },
        {
          "t": 1767196307,
          "p": -3.7277074333333333
        },
        {
          "t": 1767199911,
          "p": -3.7686169
        },
        {
          "t": 1767202760,
          "p": -3.9627998
        },
        {
          "t": 1767203344,
          "p": -4.014044466666666
        },
        {
          "t": 1767203872,
          "p": -4.0055100333333336
        },
        {
          "t": 1767207320,
          "p": -3.828217266666667
        },
        {
          "t": 1767209313,
          "p": -3.693785833333333
        },
        {
          "t": 1767210162,
          "p": -3.774684833333333
        },
        {
          "t": 1767210827,
          "p": -3.745298733333333
        },
        {
          "t": 1767213684,
          "p": -4.029047533333333
        },
        {
          "t": 1767214531,
          "p": -3.781347166666667
        },
        {
          "t": 1767216859,
          "p": -3.4549947999999997
        },
        {
          "t": 1767217599,
          "p": -3.2540820666666663
        },
        {
          "t": 1767218127,
          "p": -3.4635583666666663
        },
        {
          "t": 1767220974,
          "p": -3.9132061333333334
        },
        {
          "t": 1767221711,
          "p": -3.9701668666666667
        },
        {
          "t": 1767224060,
          "p": -3.8860932
        },
        {
          "t": 1767224961,
          "p": -3.9709726333333335
        },
        {
          "t": 1767225481,
          "p": -4.066969366666666
        },
        {
          "t": 1767241139,
          "p": -4.219899600000001
        },
        {
          "t": 1767246322,
          "p": -3.6656996666666664
        },
        {
          "t": 1767247146,
          "p": -3.4493975333333338
        },
        {
          "t": 1767250913,
          "p": -3.840308966666667
        }
      ],
      "lastAnyAt": 1767250913
    },
    "polygon:AAVE:USDC:100": {
      "samples": [
        {
          "t": 1767181597,
          "p": -1.0593540000000001
        },
        {
          "t": 1767182104,
          "p": -1.1209310000000001
        },
        {
          "t": 1767188755,
          "p": -1.171577
        },
        {
          "t": 1767189475,
          "p": -0.947675
        },
        {
          "t": 1767192244,
          "p": -1.454902
        },
        {
          "t": 1767192944,
          "p": -0.9886199999999999
        },
        {
          "t": 1767195647,
          "p": -1.266064
        },
        {
          "t": 1767196308,
          "p": -1.036075
        },
        {
          "t": 1767199913,
          "p": -1.069202
        },
        {
          "t": 1767202763,
          "p": -1.250615
        },
        {
          "t": 1767203345,
          "p": -1.25322
        },
        {
          "t": 1767203874,
          "p": -0.950571
        },
        {
          "t": 1767207322,
          "p": -1.1609
        },
        {
          "t": 1767209313,
          "p": -1.2120499999999998
        },
        {
          "t": 1767210163,
          "p": -1.3057400000000001
        },
        {
          "t": 1767210828,
          "p": -1.322119
        },
        {
          "t": 1767213685,
          "p": -1.1970049999999999
        },
        {
          "t": 1767214531,
          "p": -1.142346
        },
        {
          "t": 1767216860,
          "p": -0.950836
        },
        {
          "t": 1767217601,
          "p": -0.953858
        },
        {
          "t": 1767218129,
          "p": -0.971216
        },
        {
          "t": 1767220976,
          "p": -1.082508
        },
        {
          "t": 1767221712,
          "p": -1.118482
        },
        {
          "t": 1767224062,
          "p": -1.105656
        },
        {
          "t": 1767224962,
          "p": -1.182438
        },
        {
          "t": 1767225482,
          "p": -1.299356
        },
        {
          "t": 1767241140,
          "p": -1.2102629999999999
        },
        {
          "t": 1767246323,
          "p": -1.156366
        },
        {
          "t": 1767247147,
          "p": -1.217257
        },
        {
          "t": 1767250914,
          "p": -1.189128
        }
      ],
      "lastAnyAt": 1767250914
    },
    "polygon:AAVE:USDC:3000": {
      "samples": [
        {
          "t": 1767181600,
          "p": -5.3854020333333334
        },
        {
          "t": 1767182107,
          "p": -5.397829366666667
        },
        {
          "t": 1767188757,
          "p": -5.3755141
        },
        {
          "t": 1767189479,
          "p": -5.1915626999999995
        },
        {
          "t": 1767192249,
          "p": -5.7212404333333335
        },
        {
          "t": 1767192948,
          "p": -5.264940666666667
        },
        {
          "t": 1767195648,
          "p": -5.4380936
        },
        {
          "t": 1767196311,
          "p": -5.2131245999999996
        },
        {
          "t": 1767199916,
          "p": -5.489670733333334
        },
        {
          "t": 1767202765,
          "p": -5.4903881666666665
        },
        {
          "t": 1767203346,
          "p": -5.4320268
        },
        {
          "t": 1767203876,
          "p": -5.393773266666667
        },
        {
          "t": 1767207324,
          "p": -5.4321089
        },
        {
          "t": 1767209316,
          "p": -5.434725533333333
        },
        {
          "t": 1767210164,
          "p": -5.5266092
        },
        {
          "t": 1767210831,
          "p": -5.563310833333333
        },
        {
          "t": 1767213689,
          "p": -5.5159572
        },
        {
          "t": 1767214533,
          "p": -5.5302508
        },
        {
          "t": 1767216862,
          "p": -5.2035567333333335
        },
        {
          "t": 1767217602,
          "p": -5.209680466666667
        },
        {
          "t": 1767218131,
          "p": -5.229780466666667
        },
        {
          "t": 1767220978,
          "p": -5.306913933333333
        },
        {
          "t": 1767221713,
          "p": -5.361831366666666
        },
        {
          "t": 1767224063,
          "p": -5.4242801
        },
        {
          "t": 1767224964,
          "p": -5.448513733333334
        },
        {
          "t": 1767225484,
          "p": -5.499743866666667
        },
        {
          "t": 1767241142,
          "p": -5.474942466666667
        },
        {
          "t": 1767246325,
          "p": -5.420030733333333
        },
        {
          "t": 1767247149,
          "p": -5.4219286
        },
        {
          "t": 1767250915,
          "p": -5.480422066666667
        }
      ],
      "lastAnyAt": 1767250915
    }
  },
  "meta": {
    "lastAnySentAt": 1767078041
  }
}